flake8_test_name.py
flake8_test_name-0.1.6.dist-info/LICENSE
flake8_test_name-0.1.6.dist-info/METADATA
flake8_test_name-0.1.6.dist-info/WHEEL
flake8_test_name-0.1.6.dist-info/entry_points.txt
flake8_test_name-0.1.6.dist-info/top_level.txt
flake8_test_name-0.1.6.dist-info/RECORD
