Metadata-Version: 2.1
Name: flake8-test-name
Version: 0.1.6
Summary: Invalid test name checker, plugin for flake8
Home-page: https://github.com/bagerard/flake8-test-name
Maintainer: Bastien Gerard
Maintainer-email: bast.gerard@gmail.com
License: MIT License
Keywords: flake8 test name convention
Platform: UNKNOWN
Classifier: Development Status :: 3 - Alpha
Classifier: Environment :: Console
Classifier: Intended Audience :: Developers
Classifier: License :: OSI Approved :: MIT License
Classifier: Operating System :: OS Independent
Classifier: Programming Language :: Python
Classifier: Programming Language :: Python :: 3
Classifier: Topic :: Software Development :: Libraries :: Python Modules
Classifier: Topic :: Software Development :: Quality Assurance
License-File: LICENSE
Requires-Dist: flake8
